commands/__init__.py
commands/fuse_sharepoint.py
remote_fuse/__init__.py
remote_fuse/core.py
remote_fuse/exceptions.py
remote_fuse/logging.py
remote_fuse/sharepoint.py
remote_fuse/utils.py
remote_fuse-0.1.6.dist-info/licenses/LICENSE
remote_fuse-0.1.6.dist-info/METADATA
remote_fuse-0.1.6.dist-info/WHEEL
remote_fuse-0.1.6.dist-info/entry_points.txt
remote_fuse-0.1.6.dist-info/top_level.txt
remote_fuse-0.1.6.dist-info/RECORD
