Metadata-Version: 2.4
Name: remote-fuse
Version: 0.1.6
Summary: Mount remote cloud storage as FUSE filesystem
License-Expression: Apache-2.0
Requires-Python: >=3.10
License-File: LICENSE
Requires-Dist: azure-identity>=1.21.0
Requires-Dist: fuse-python>=1.0.9
Requires-Dist: msgraph-sdk>=1.26.0
Provides-Extra: test
Requires-Dist: pytest>=8.3.5; extra == "test"
Requires-Dist: pytest-asyncio>=0.25.0; extra == "test"
Dynamic: license-file
